vtk_python_docs/__init__.py
vtk_python_docs/build.py
vtk_python_docs/cli.py
vtk_python_docs/config.py
vtk_python_docs/extract/__init__.py
vtk_python_docs/extract/extractor.py
vtk_python_docs/extract/introspection.py
vtk_python_docs/extract/llm.py
vtk_python_docs/markdown/__init__.py
vtk_python_docs/markdown/generator.py
vtk_python_docs/stubs/__init__.py
vtk_python_docs/stubs/enhance.py
vtk_python_docs-0.3.0.dist-info/METADATA
vtk_python_docs-0.3.0.dist-info/WHEEL
vtk_python_docs-0.3.0.dist-info/entry_points.txt
vtk_python_docs-0.3.0.dist-info/licenses/LICENSE
vtk_python_docs-0.3.0.dist-info/RECORD
