Metadata-Version: 2.4
Name: vtk-python-docs
Version: 0.3.0
Summary: VTK Python documentation extraction, stub enhancement, and API generation
Project-URL: Homepage, https://github.com/patrickoleary/vtk-python-docs
Project-URL: Repository, https://github.com/patrickoleary/vtk-python-docs
Project-URL: Issues, https://github.com/patrickoleary/vtk-python-docs/issues
Author-email: Patrick O'Leary <patrick.oleary@kitware.com>
License: MIT License
License-File: LICENSE
Keywords: documentation,pyi,stubs,type-hints,visualization,vtk
Classifier: Development Status :: 3 - Alpha
Classifier: Intended Audience :: Developers
Classifier: License :: OSI Approved :: MIT License
Classifier: Programming Language :: Python :: 3
Classifier: Programming Language :: Python :: 3.10
Classifier: Programming Language :: Python :: 3.11
Classifier: Programming Language :: Python :: 3.12
Classifier: Programming Language :: Python :: 3.13
Classifier: Topic :: Documentation
Classifier: Topic :: Scientific/Engineering :: Visualization
Classifier: Topic :: Software Development :: Documentation
Requires-Python: >=3.10
Requires-Dist: litellm>=1.0.0
Requires-Dist: python-dotenv>=1.0.0
Requires-Dist: typer>=0.12.0
Requires-Dist: vtk>=9.0.0
Provides-Extra: dev
Requires-Dist: pyright>=1.1.0; extra == 'dev'
Requires-Dist: pytest-asyncio>=0.23.0; extra == 'dev'
Requires-Dist: pytest-cov>=4.0.0; extra == 'dev'
Requires-Dist: pytest>=7.0.0; extra == 'dev'
Requires-Dist: ruff>=0.1.0; extra == 'dev'
Requires-Dist: vulture>=2.0; extra == 'dev'
